README.md
setup.py
wanmedia/__init__.py
wanmedia/datacollection.py
wanmedia/datavis.py
wanmedia/network.py
wanmedia/sentiment.py
wanmedia/sys.py
wanmedia/textfeature.py
wanmedia/textprocessing.py
wanmedia/topicmodel.py
wanmedia.egg-info/PKG-INFO
wanmedia.egg-info/SOURCES.txt
wanmedia.egg-info/dependency_links.txt
wanmedia.egg-info/requires.txt
wanmedia.egg-info/top_level.txt